pgbitmapfont/__init__.py
pgbitmapfont/bitmapfont_fixed_height.py
pgbitmapfont/bitmapfont_free_dims.py
pgbitmapfont/extractor.py
pgbitmapfont-0.1.6.dist-info/licenses/LICENSE
pgbitmapfont-0.1.6.dist-info/METADATA
pgbitmapfont-0.1.6.dist-info/WHEEL
pgbitmapfont-0.1.6.dist-info/entry_points.txt
pgbitmapfont-0.1.6.dist-info/top_level.txt
pgbitmapfont-0.1.6.dist-info/RECORD
