Metadata-Version: 2.4
Name: pgbitmapfont
Version: 0.1.6
Summary: A Python library to render text from bitmap font images
Author: xdoko01
License: MIT
Project-URL: Homepage, https://github.com/xdoko01/Pygame-BitmapFont
Project-URL: Issues, https://github.com/xdoko01/Pygame-BitmapFont/issues
Requires-Python: >=3.7
License-File: LICENSE
Requires-Dist: pygame-ce
Requires-Dist: pathlib
Dynamic: license-file
